basket_case/__init__.py
basket_case/basket.py
basket_case_pynchia-0.1.0.dist-info/METADATA
basket_case_pynchia-0.1.0.dist-info/WHEEL
basket_case_pynchia-0.1.0.dist-info/licenses/LICENSE
basket_case_pynchia-0.1.0.dist-info/RECORD
