Metadata-Version: 2.1
Name: basket_case_pynchia
Version: 0.1.0
Summary: A lib to fit objects of different size into multiple baskets (of the same size) optimally. For example, use it to backup contents to CDs, DVDs, USB sticks, etc
Author-Email: pynchia <pynchia@gmail.com>
License: MIT
Classifier: Programming Language :: Python :: 3
Classifier: License :: OSI Approved :: MIT License
Classifier: Operating System :: OS Independent
Project-URL: Homepage, https://gitlab.com/pynchia/basket_case
Project-URL: Issues, https://gitlab.com/pynchia/basket_case/-/issues
Requires-Python: >=3.11
